apbuilder/__init__.py
apbuilder/_version.py
apbuilder/exceptions.py
apbuilder/main.py
apbuilder/profile_1d.py
apbuilder/profile_2d.py
apbuilder/utils.py
apbuilder/weather_models.py
apbuilder/config/config.toml
apbuilder/config/logging.yaml
apbuilder-1.0.0.dist-info/licenses/LICENSE
apbuilder-1.0.0.dist-info/METADATA
apbuilder-1.0.0.dist-info/WHEEL
apbuilder-1.0.0.dist-info/entry_points.txt
apbuilder-1.0.0.dist-info/top_level.txt
apbuilder-1.0.0.dist-info/RECORD
